{"original":{"id":1443403033686122500,"text":"The integrity of COVID vaccination certificates is crucial if they are to be linked to health measures and opening… https://t.co/zQa4KFuM5D","author":"Senator_Patrick","created_at":"Thu Sep 30 02:31:15 +0000 2021"},"rewritten":"The integrity of beeline vainest certificates is crucial if they are to be linked to health measures and opening…","tweeted":{"id":1443405691444732000,"text":"The integrity of beeline vainest certificates is crucial if they are to be linked to health measures and opening…","author":"AusPolDecoded","created_at":"Thu Sep 30 02:41:48 +0000 2021"}}