{"original":{"id":1443014650962976800,"text":"The Parliamentary Joint Committee on Intelligence and Security has tabled its report into the Security of Critical… https://t.co/9CuVRiqcZa","author":"SenPaterson","created_at":"Wed Sep 29 00:47:57 +0000 2021"},"rewritten":"The Parliamentary Joint Committee on Intelligence and Security has tabled its report into the Security of crossest…","tweeted":{"id":1443031063211745300,"text":"The Parliamentary Joint Committee on Intelligence and Security has tabled its report into the Security of crossest…","author":"AusPolDecoded","created_at":"Wed Sep 29 01:53:10 +0000 2021"}}