{"original":{"id":1447515849305198600,"text":"Murdoch now says deploying green technology, like electric vehicles, can create 672,000 new jobs by 2050. Funny – w… https://t.co/JuIxzqYjQS","author":"MrKRudd","created_at":"Mon Oct 11 10:54:06 +0000 2021"},"rewritten":"Murdoch now says deploying green technology, like electric vehicles, can create 672,000 new jocosities by 2050. furniture – w…","tweeted":{"id":1447520275373957000,"text":"Murdoch now says deploying green technology, like electric vehicles, can create 672,000 new jocosities by 2050. fur… https://t.co/O7ILGJVp3a","author":"AusPolDecoded","created_at":"Mon Oct 11 11:11:41 +0000 2021"}}