{"original":{"id":1447747422952702000,"text":"Just 9 countries in the world have a net zero target in law ... the others just say trust ... even though barely an… https://t.co/lRghDwewUH","author":"mattjcan","created_at":"Tue Oct 12 02:14:18 +0000 2021"},"rewritten":"Just 9 countries in the world have a net zero target in law ... the others just say trust ... even though baser an…","tweeted":{"id":1447754435783012400,"text":"Just 9 countries in the world have a net zero target in law ... the others just say trust ... even though baser an…","author":"AusPolDecoded","created_at":"Tue Oct 12 02:42:10 +0000 2021"}}