{"original":{"id":1455791877643378700,"text":"From tomorrow, if you get your first dose at one of these vaccine hubs, you will receive a $10 voucher to a partici… https://t.co/aj7JcXTvhj","author":"AnnastaciaMP","created_at":"Wed Nov 03 07:00:05 +0000 2021"},"rewritten":"From tomorrow, if you get your first dose at one of these vagary hubs, you will receive a $10 voucher to a partici…","tweeted":{"id":1455796012212228000,"text":"From tomorrow, if you get your first dose at one of these vagary hubs, you will receive a $10 voucher to a partici…","author":"AusPolDecoded","created_at":"Wed Nov 03 07:16:31 +0000 2021"}}