{"original":{"id":1456048563742392300,"text":"The Premier and the Acting Chief Health Officer are giving a COVID-19 update in Logan. #covid19 https://t.co/1TASGmCuGx","author":"AnnastaciaMP","created_at":"Thu Nov 04 00:00:04 +0000 2021"},"rewritten":"The Premier and the activist Chief Health Officer are giving a COVID-19 update in Logan. #covid19 https://t.co/1TASGmCuGx","tweeted":{"id":1456060919939801000,"text":"The Premier and the activist Chief Health Officer are giving a COVID-19 update in Logan. #covid19… https://t.co/yLFNQFLyNe","author":"AusPolDecoded","created_at":"Thu Nov 04 00:49:10 +0000 2021"}}