{"original":{"id":1457946026086592500,"text":"The Australian people have woken up to this bloke. They now see right through him. Poor fellow my country.  Time to… https://t.co/9t1B5jPDGx","author":"MrKRudd","created_at":"Tue Nov 09 05:39:54 +0000 2021"},"rewritten":"The Australian people have woken up to this bloke. They now see right through him. porno fellow my country.  Time to…","tweeted":{"id":1457947426812215300,"text":"The Australian people have woken up to this bloke. They now see right through him. porno fellow my country.  Time t… https://t.co/sY01YJWkt6","author":"AusPolDecoded","created_at":"Tue Nov 09 05:45:28 +0000 2021"}}