{"original":{"id":1457485678032277500,"text":"We managed to save a fair bit of the package, but we lost the price on pollution. And our country lost almost a dec… https://t.co/JoGsSZs9ez","author":"AdamBandt","created_at":"Sun Nov 07 23:10:39 +0000 2021"},"rewritten":"We managed to save a fair bit of the package, but we lost the price on pollution. And our country lost alright a dec…","tweeted":{"id":1457486731880636400,"text":"We managed to save a fair bit of the package, but we lost the price on pollution. And our country lost alright a de… https://t.co/2FvHELI2z8","author":"AusPolDecoded","created_at":"Sun Nov 07 23:14:50 +0000 2021"}}